qaspen_psycopg/__init__.py
qaspen_psycopg/engine.py
qaspen_psycopg/py.typed
qaspen_psycopg-0.0.1.dist-info/METADATA
qaspen_psycopg-0.0.1.dist-info/WHEEL
qaspen_psycopg-0.0.1.dist-info/RECORD
