Metadata-Version: 2.1
Name: qaspen-psycopg
Version: 0.0.1
Summary: 
Author: chandr-andr (Kiselev Aleksandr)
Author-email: askiselev00@gmail.com
Requires-Python: >=3.8.1,<4.0
Classifier: Programming Language :: Python :: 3
Classifier: Programming Language :: Python :: 3.9
Classifier: Programming Language :: Python :: 3.10
Classifier: Programming Language :: Python :: 3.11
Classifier: Programming Language :: Python :: 3.12
Requires-Dist: psycopg (>=3.1.12,<4.0.0)
Requires-Dist: psycopg-pool (>=3.1.8,<4.0.0)
Requires-Dist: qaspen (>=0.0.5a0,<0.0.6)
